new_python_sdk-5.0.7.dist-info/licenses/LICENCE
test/__init__.py
test/test_account.py
test/test_events.py
test/test_hooks.py
test/test_images.py
test/test_locations.py
test/test_profiles.py
test/test_scripts.py
test/test_servers.py
test/test_shellusers.py
test/test_snapshots.py
test/test_sshkeys.py
webdock/__init__.py
webdock/account.py
webdock/events.py
webdock/hooks.py
webdock/images.py
webdock/locations.py
webdock/operation.py
webdock/profiles.py
webdock/scripts.py
webdock/servers.py
webdock/shellusers.py
webdock/snapshots.py
webdock/sshkeys.py
new_python_sdk-5.0.7.dist-info/METADATA
new_python_sdk-5.0.7.dist-info/WHEEL
new_python_sdk-5.0.7.dist-info/top_level.txt
new_python_sdk-5.0.7.dist-info/RECORD
